[
  {
    "artist": "George Ezra",
    "title": "Come On Home For Christmas",
    "startTime": "2025-12-05T18:20:00Z",
    "source": "PLAYIT"
  },
  {
    "artist": "Andy Williams",
    "title": "It's the Most Wonderful Time of the Year",
    "startTime": "2025-12-05T18:22:52Z",
    "source": "PLAYIT"
  },
  {
    "artist": "Ed Sheeran",
    "title": "Under The Tree (From \"That Christmas\")",
    "startTime": "2025-12-05T18:25:18Z",
    "source": "PLAYIT"
  },
  {
    "artist": "Frank Sinatra",
    "title": "Have Yourself a Merry Little Christmas",
    "startTime": "2025-12-05T18:29:06Z",
    "source": "PLAYIT"
  },
  {
    "artist": "The Jackson 5",
    "title": "Santa Claus Is Coming to Town",
    "startTime": "2025-12-05T18:32:58Z",
    "source": "PLAYIT"
  },
  {
    "artist": "Wizzard",
    "title": "I Wish It Could Be Christmas Everyday",
    "startTime": "2025-12-05T18:39:20Z",
    "source": "PLAYIT"
  },
  {
    "artist": "V, Park Hyo Shin",
    "title": "Winter Ahead",
    "startTime": "2025-12-05T18:43:47Z",
    "source": "PLAYIT"
  },
  {
    "artist": "Destiny's Child",
    "title": "Little Drummer Boy",
    "startTime": "2025-12-05T18:47:30Z",
    "source": "PLAYIT"
  },
  {
    "artist": "Michael Buble",
    "title": "It's Beginning to Look a Lot Like Christmas",
    "startTime": "2025-12-05T18:50:56Z",
    "source": "PLAYIT"
  },
  {
    "artist": "Bryan Adams",
    "title": "Christmas Time",
    "startTime": "2025-12-05T18:53:44Z",
    "source": "PLAYIT"
  },
  {
    "artist": "Bryan Adams",
    "title": "Christmas Time",
    "startTime": "2025-12-05T19:00:07Z",
    "source": "ALT",
    "live": true
  },
  {
    "artist": "Lee Everest",
    "title": "Ready for the Weekend",
    "startTime": "2025-12-05T19:02:02Z",
    "source": "ALT",
    "live": true
  },
  {
    "artist": "Yes Boone",
    "title": "All I Really Want",
    "startTime": "2025-12-05T19:03:03Z",
    "source": "ALT",
    "live": true
  },
  {
    "artist": "Casso & Sacha",
    "title": "Guest List",
    "startTime": "2025-12-05T19:06:11Z",
    "source": "ALT",
    "live": true
  },
  {
    "artist": "Body Ocean",
    "title": "What Would It Profit",
    "startTime": "2025-12-05T19:08:37Z",
    "source": "ALT",
    "live": true
  },
  {
    "artist": "Mike Mago",
    "title": "Dangerous Behaviour (VIP Mix)",
    "startTime": "2025-12-05T19:12:29Z",
    "source": "ALT",
    "live": true
  },
  {
    "artist": "Kx5 & AR/CO",
    "title": "Bright Lights",
    "startTime": "2025-12-05T19:15:37Z",
    "source": "ALT",
    "live": true
  },
  {
    "artist": "Ed Sheeran",
    "title": "Azizam (Navos Remix)",
    "startTime": "2025-12-05T19:18:57Z",
    "source": "ALT",
    "live": true
  },
  {
    "artist": "Lee Everest",
    "title": "Ready for the Weekend",
    "startTime": "2025-12-05T19:23:01Z",
    "source": "ALT",
    "live": true
  },
  {
    "artist": "STIRLING & Dan Diamond",
    "title": "I Got Bad Habits",
    "startTime": "2025-12-05T19:23:16Z",
    "source": "ALT",
    "live": true
  }
]