[
  {
    "artist": "Callum Beattie",
    "title": "Two Pretenders",
    "startTime": "2025-12-01T05:23:15Z",
    "source": "PLAYIT"
  },
  {
    "artist": "Beyonce",
    "title": "Irreplaceable",
    "startTime": "2025-12-01T05:26:42Z",
    "source": "PLAYIT"
  },
  {
    "artist": "Charli XCX",
    "title": "Chains of Love",
    "startTime": "2025-12-01T05:30:17Z",
    "source": "PLAYIT"
  },
  {
    "artist": "Taylor Swift",
    "title": "Anti-Hero",
    "startTime": "2025-12-01T05:33:08Z",
    "source": "PLAYIT"
  },
  {
    "artist": "Olivia Dean",
    "title": "The Christmas Song",
    "startTime": "2025-12-01T05:36:21Z",
    "source": "PLAYIT"
  },
  {
    "artist": "Meghan Trainor",
    "title": "Made You Look",
    "startTime": "2025-12-01T05:43:14Z",
    "source": "PLAYIT"
  },
  {
    "artist": "Pulp",
    "title": "Common People",
    "startTime": "2025-12-01T05:45:31Z",
    "source": "PLAYIT"
  },
  {
    "artist": "Shaboozey",
    "title": "A Bar Song (Tipsy)",
    "startTime": "2025-12-01T05:49:23Z",
    "source": "PLAYIT"
  },
  {
    "artist": "Kygo Feat. Conrad Sewell",
    "title": "Firestone",
    "startTime": "2025-12-01T05:52:15Z",
    "source": "PLAYIT"
  },
  {
    "artist": "Ariana Grande",
    "title": "One Last Time",
    "startTime": "2025-12-01T05:55:30Z",
    "source": "PLAYIT"
  },
  {
    "artist": "Ed Sheeran",
    "title": "Camera",
    "startTime": "2025-12-01T06:01:35Z",
    "source": "PLAYIT"
  },
  {
    "artist": "Nectar Woode",
    "title": "When The Rain Stops",
    "startTime": "2025-12-01T06:05:41Z",
    "source": "PLAYIT"
  },
  {
    "artist": "Tom Grennan",
    "title": "How Does It Feel",
    "startTime": "2025-12-01T06:08:51Z",
    "source": "PLAYIT"
  },
  {
    "artist": "Mark Ronson ft Amy Winehouse",
    "title": "Valerie",
    "startTime": "2025-12-01T06:11:08Z",
    "source": "PLAYIT"
  },
  {
    "artist": "Olivia Rodrigo",
    "title": "Good 4 U",
    "startTime": "2025-12-01T06:14:42Z",
    "source": "PLAYIT"
  },
  {
    "artist": "Sabrina Carpenter",
    "title": "Busy Woman",
    "startTime": "2025-12-01T06:21:46Z",
    "source": "PLAYIT"
  },
  {
    "artist": "Rihanna",
    "title": "Only Girl (In the World)",
    "startTime": "2025-12-01T06:24:52Z",
    "source": "PLAYIT"
  },
  {
    "artist": "Mud",
    "title": "Lonely This Christmas",
    "startTime": "2025-12-01T06:31:55Z",
    "source": "PLAYIT"
  },
  {
    "artist": "Ella Henderson x Alex Warren",
    "title": "Carry You Home",
    "startTime": "2025-12-01T06:35:22Z",
    "source": "PLAYIT"
  },
  {
    "artist": "Calvin Harris & Clementine Douglas",
    "title": "Blessings",
    "startTime": "2025-12-01T06:42:31Z",
    "source": "PLAYIT"
  }
]