[
  {
    "artist": "Usher",
    "title": "Burn",
    "startTime": "2025-11-06T16:52:53Z",
    "source": "PLAYIT"
  },
  {
    "artist": "David Guetta/Teddy Swims/Tones and I",
    "title": "Gone Gone Gone",
    "startTime": "2025-11-06T17:03:03Z",
    "source": "PLAYIT"
  },
  {
    "artist": "Lewis Capaldi",
    "title": "Survive",
    "startTime": "2025-11-06T17:06:48Z",
    "source": "PLAYIT"
  },
  {
    "artist": "Perrie",
    "title": "Forget About Us",
    "startTime": "2025-11-06T17:10:26Z",
    "source": "PLAYIT"
  },
  {
    "artist": "Vanessa Carlton",
    "title": "A Thousand Miles",
    "startTime": "2025-11-06T17:13:44Z",
    "source": "PLAYIT"
  },
  {
    "artist": "Joel Corry & Becky Hill",
    "title": "HISTORY",
    "startTime": "2025-11-06T17:17:35Z",
    "source": "PLAYIT"
  },
  {
    "artist": "George Ezra",
    "title": "Green Green Grass",
    "startTime": "2025-11-06T17:23:37Z",
    "source": "PLAYIT"
  },
  {
    "artist": "The Fratellis",
    "title": "Chelsea Dagger",
    "startTime": "2025-11-06T17:26:41Z",
    "source": "PLAYIT"
  },
  {
    "artist": "Jingle",
    "title": "Doing It The Ayrshire Way V2",
    "startTime": "2025-11-06T17:33:12Z",
    "source": "PLAYIT"
  },
  {
    "artist": "Chappell Roan",
    "title": "Pink Pony Club",
    "startTime": "2025-11-06T17:33:20Z",
    "source": "PLAYIT"
  },
  {
    "artist": "KPop Demon Hunters",
    "title": "Golden",
    "startTime": "2025-11-06T17:37:30Z",
    "source": "PLAYIT"
  },
  {
    "artist": "Ed Sheeran",
    "title": "Bad Habits",
    "startTime": "2025-11-06T17:44:25Z",
    "source": "PLAYIT"
  },
  {
    "artist": "Black Box",
    "title": "Ride on Time",
    "startTime": "2025-11-06T17:48:30Z",
    "source": "PLAYIT"
  },
  {
    "artist": "Kings Of Leon",
    "title": "Use Somebody",
    "startTime": "2025-11-06T17:52:48Z",
    "source": "PLAYIT"
  },
  {
    "artist": "Olivia Dean",
    "title": "Man I Need",
    "startTime": "2025-11-06T18:01:44Z",
    "source": "PLAYIT"
  },
  {
    "artist": "Disco Lines & Tinashe",
    "title": "No Broke Boys",
    "startTime": "2025-11-06T18:04:54Z",
    "source": "PLAYIT"
  },
  {
    "artist": "Amy Macdonald",
    "title": "I'm Done (Games That You Play)",
    "startTime": "2025-11-06T18:07:35Z",
    "source": "PLAYIT"
  },
  {
    "artist": "Anne-Marie ft Shania Twain",
    "title": "Unhealthy",
    "startTime": "2025-11-06T18:10:46Z",
    "source": "PLAYIT"
  },
  {
    "artist": "MK ft Chrystal",
    "title": "Dior",
    "startTime": "2025-11-06T18:13:16Z",
    "source": "PLAYIT"
  },
  {
    "artist": "Sabrina Carpenter",
    "title": "Tears",
    "startTime": "2025-11-06T18:20:24Z",
    "source": "PLAYIT"
  }
]