[
  {
    "artist": "Wet Leg",
    "title": "Catch These Fists",
    "startTime": "2025-11-21T09:30:37Z",
    "source": "PLAYIT"
  },
  {
    "artist": "Amy Macdonald",
    "title": "Mr Rock & Roll",
    "startTime": "2025-11-21T09:33:50Z",
    "source": "PLAYIT"
  },
  {
    "artist": "RAYE",
    "title": "Where Is My Husband!",
    "startTime": "2025-11-21T09:37:20Z",
    "source": "PLAYIT"
  },
  {
    "artist": "George Ezra",
    "title": "Green Green Grass",
    "startTime": "2025-11-21T09:41:48Z",
    "source": "PLAYIT"
  },
  {
    "artist": "BLACKPINK",
    "title": "Jump",
    "startTime": "2025-11-21T09:44:34Z",
    "source": "PLAYIT"
  },
  {
    "artist": "Lady Gaga",
    "title": "Abracadabra",
    "startTime": "2025-11-21T09:52:47Z",
    "source": "PLAYIT"
  },
  {
    "artist": "Ace of Base",
    "title": "All That She Wants",
    "startTime": "2025-11-21T09:56:26Z",
    "source": "PLAYIT"
  },
  {
    "artist": "KPop Demon Hunters",
    "title": "Golden",
    "startTime": "2025-11-21T10:02:10Z",
    "source": "PLAYIT"
  },
  {
    "artist": "Dua Lipa",
    "title": "Houdini",
    "startTime": "2025-11-21T10:11:13Z",
    "source": "PLAYIT"
  },
  {
    "artist": "Stereophonics",
    "title": "Dakota",
    "startTime": "2025-11-21T10:14:14Z",
    "source": "PLAYIT"
  },
  {
    "artist": "Tom Grennan",
    "title": "All These Nights",
    "startTime": "2025-11-21T10:18:20Z",
    "source": "PLAYIT"
  },
  {
    "artist": "Dasha",
    "title": "Austin (Boots Stop Workin')",
    "startTime": "2025-11-21T10:27:23Z",
    "source": "PLAYIT"
  },
  {
    "artist": "Alex Warren",
    "title": "Eternity",
    "startTime": "2025-11-21T10:30:10Z",
    "source": "PLAYIT"
  },
  {
    "artist": "No Doubt",
    "title": "Don't Speak",
    "startTime": "2025-11-21T10:33:22Z",
    "source": "PLAYIT"
  },
  {
    "artist": "Bjork",
    "title": "It's Oh So Quiet",
    "startTime": "2025-11-21T10:38:17Z",
    "source": "PLAYIT"
  },
  {
    "artist": "Blur",
    "title": "Parklife",
    "startTime": "2025-11-21T10:42:02Z",
    "source": "PLAYIT"
  },
  {
    "artist": "Carly Rae Jepsen",
    "title": "Call Me Maybe",
    "startTime": "2025-11-21T10:45:03Z",
    "source": "PLAYIT"
  },
  {
    "artist": "Perrie",
    "title": "Rocket Scientist",
    "startTime": "2025-11-21T10:51:53Z",
    "source": "PLAYIT"
  },
  {
    "artist": "Sekou",
    "title": "Catching Bodies",
    "startTime": "2025-11-21T10:55:17Z",
    "source": "PLAYIT"
  },
  {
    "artist": "Ariana Grande",
    "title": "No Tears Left to Cry",
    "startTime": "2025-11-21T11:02:30Z",
    "source": "PLAYIT"
  }
]