[
  {
    "artist": "Ace of Base",
    "title": "All That She Wants",
    "startTime": "2025-12-10T08:52:51Z",
    "source": "PLAYIT"
  },
  {
    "artist": "Beyonce",
    "title": "Single Ladies (Put a Ring on It)",
    "startTime": "2025-12-10T08:56:13Z",
    "source": "PLAYIT"
  },
  {
    "artist": "Justin Bieber",
    "title": "Mistletoe",
    "startTime": "2025-12-10T09:03:15Z",
    "source": "PLAYIT"
  },
  {
    "artist": "Coldplay",
    "title": "Feels Like I'm Falling in Love",
    "startTime": "2025-12-10T09:06:15Z",
    "source": "PLAYIT"
  },
  {
    "artist": "Sabrina Carpenter",
    "title": "Busy Woman",
    "startTime": "2025-12-10T09:11:18Z",
    "source": "PLAYIT"
  },
  {
    "artist": "Dua Lipa",
    "title": "Levitating",
    "startTime": "2025-12-10T09:14:19Z",
    "source": "PLAYIT"
  },
  {
    "artist": "Queen",
    "title": "Don't Stop Me Now",
    "startTime": "2025-12-10T09:17:49Z",
    "source": "PLAYIT"
  },
  {
    "artist": "Jonas Brothers",
    "title": "Like It's Christmas",
    "startTime": "2025-12-10T09:27:15Z",
    "source": "PLAYIT"
  },
  {
    "artist": "Tate McRae",
    "title": "Just Keep Watching",
    "startTime": "2025-12-10T09:30:31Z",
    "source": "PLAYIT"
  },
  {
    "artist": "Alicia Keys",
    "title": "No One",
    "startTime": "2025-12-10T09:33:01Z",
    "source": "PLAYIT"
  },
  {
    "artist": "Olivia Dean",
    "title": "So Easy (To Fall In Love)",
    "startTime": "2025-12-10T09:37:58Z",
    "source": "PLAYIT"
  },
  {
    "artist": "Harry Styles",
    "title": "Adore You",
    "startTime": "2025-12-10T09:40:50Z",
    "source": "PLAYIT"
  },
  {
    "artist": "Sammy Virji & Chris Lake",
    "title": "925",
    "startTime": "2025-12-10T09:44:15Z",
    "source": "PLAYIT"
  },
  {
    "artist": "The Waitresses",
    "title": "Christmas Wrapping",
    "startTime": "2025-12-10T09:52:22Z",
    "source": "PLAYIT"
  },
  {
    "artist": "Bon Jovi",
    "title": "Livin' on a Prayer",
    "startTime": "2025-12-10T09:56:12Z",
    "source": "PLAYIT"
  },
  {
    "artist": "Myles Smith",
    "title": "Stay (If You Wanna Dance)",
    "startTime": "2025-12-10T10:02:15Z",
    "source": "PLAYIT"
  },
  {
    "artist": "Queen",
    "title": "I Want to Break Free",
    "startTime": "2025-12-10T10:06:09Z",
    "source": "PLAYIT"
  },
  {
    "artist": "Taylor Swift",
    "title": "Cruel Summer",
    "startTime": "2025-12-10T10:11:52Z",
    "source": "PLAYIT"
  },
  {
    "artist": "Mary J Blige",
    "title": "Family Affair",
    "startTime": "2025-12-10T10:14:47Z",
    "source": "PLAYIT"
  },
  {
    "artist": "Jona Lewie",
    "title": "Stop the Cavalry",
    "startTime": "2025-12-10T10:18:12Z",
    "source": "PLAYIT"
  }
]