[
  {
    "artist": "Myles Smith",
    "title": "Nice To Meet You",
    "startTime": "2025-11-26T17:37:50Z",
    "source": "PLAYIT"
  },
  {
    "artist": "Hozier",
    "title": "Too Sweet",
    "startTime": "2025-11-26T17:44:44Z",
    "source": "PLAYIT"
  },
  {
    "artist": "Madonna",
    "title": "Like a Prayer",
    "startTime": "2025-11-26T17:49:00Z",
    "source": "PLAYIT"
  },
  {
    "artist": "Amy Winehouse",
    "title": "Back to Black",
    "startTime": "2025-11-26T17:54:05Z",
    "source": "PLAYIT"
  },
  {
    "artist": "Lewis Capaldi",
    "title": "Something In The Heavens",
    "startTime": "2025-11-26T18:01:49Z",
    "source": "PLAYIT"
  },
  {
    "artist": "Benson Boone",
    "title": "Sorry I'm Here For Someone Else",
    "startTime": "2025-11-26T18:05:09Z",
    "source": "PLAYIT"
  },
  {
    "artist": "Sekou",
    "title": "Catching Bodies",
    "startTime": "2025-11-26T18:07:44Z",
    "source": "PLAYIT"
  },
  {
    "artist": "MK ft Chrystal",
    "title": "Dior",
    "startTime": "2025-11-26T18:10:52Z",
    "source": "PLAYIT"
  },
  {
    "artist": "Sam Ryder",
    "title": "Better Man",
    "startTime": "2025-11-26T18:13:42Z",
    "source": "PLAYIT"
  },
  {
    "artist": "Calvin Harris & Jessie Reyez",
    "title": "Ocean",
    "startTime": "2025-11-26T18:20:54Z",
    "source": "PLAYIT"
  },
  {
    "artist": "Becky Hill ft Topic",
    "title": "My Heart Goes (La Di Da)",
    "startTime": "2025-11-26T18:24:30Z",
    "source": "PLAYIT"
  },
  {
    "artist": "BLACKPINK",
    "title": "Jump",
    "startTime": "2025-11-26T18:27:00Z",
    "source": "PLAYIT"
  },
  {
    "artist": "Nectar Woode",
    "title": "When The Rain Stops",
    "startTime": "2025-11-26T18:29:42Z",
    "source": "PLAYIT"
  },
  {
    "artist": "Caity Baser",
    "title": "Running From Myself",
    "startTime": "2025-11-26T18:32:48Z",
    "source": "PLAYIT"
  },
  {
    "artist": "Dua Lipa",
    "title": "Dance The Night",
    "startTime": "2025-11-26T18:35:26Z",
    "source": "PLAYIT"
  },
  {
    "artist": "Chappell Roan",
    "title": "Pink Pony Club",
    "startTime": "2025-11-26T18:42:11Z",
    "source": "PLAYIT"
  },
  {
    "artist": "Ed Sheeran",
    "title": "Camera",
    "startTime": "2025-11-26T18:46:18Z",
    "source": "PLAYIT"
  },
  {
    "artist": "Sophie Ellis-Bextor",
    "title": "Stay On Me",
    "startTime": "2025-11-26T18:49:55Z",
    "source": "PLAYIT"
  },
  {
    "artist": "Taylor Swift",
    "title": "Opalite",
    "startTime": "2025-11-26T18:53:00Z",
    "source": "PLAYIT"
  },
  {
    "artist": "Janet Jackson",
    "title": "Someone To Call My Lover",
    "startTime": "2025-11-26T19:01:51Z",
    "source": "PLAYIT"
  }
]