[
  {
    "artist": "Sam Ryder",
    "title": "Better Man",
    "startTime": "2025-12-13T07:01:53Z",
    "source": "PLAYIT"
  },
  {
    "artist": "KPop Demon Hunters",
    "title": "Golden",
    "startTime": "2025-12-13T07:05:32Z",
    "source": "PLAYIT"
  },
  {
    "artist": "Nat King Cole",
    "title": "The Christmas Song (Chestnuts Roasting on an Open Fire)",
    "startTime": "2025-12-13T07:08:40Z",
    "source": "PLAYIT"
  },
  {
    "artist": "Adele",
    "title": "Send My Love (To Your New Lover)",
    "startTime": "2025-12-13T07:11:46Z",
    "source": "PLAYIT"
  },
  {
    "artist": "Perrie",
    "title": "If He Wanted To He Would",
    "startTime": "2025-12-13T07:15:22Z",
    "source": "PLAYIT"
  },
  {
    "artist": "Chris Rea",
    "title": "Driving Home for Christmas",
    "startTime": "2025-12-13T07:23:00Z",
    "source": "PLAYIT"
  },
  {
    "artist": "Manic Street Preachers",
    "title": "A Design for Life",
    "startTime": "2025-12-13T07:26:48Z",
    "source": "PLAYIT"
  },
  {
    "artist": "Demi Lovato",
    "title": "Here All Night",
    "startTime": "2025-12-13T07:31:01Z",
    "source": "PLAYIT"
  },
  {
    "artist": "Maroon 5",
    "title": "Memories",
    "startTime": "2025-12-13T07:34:19Z",
    "source": "PLAYIT"
  },
  {
    "artist": "Ed Sheeran & Elton John",
    "title": "Merry Christmas",
    "startTime": "2025-12-13T07:37:21Z",
    "source": "PLAYIT"
  },
  {
    "artist": "Pink",
    "title": "Never Gonna Not Dance Again",
    "startTime": "2025-12-13T07:44:13Z",
    "source": "PLAYIT"
  },
  {
    "artist": "Space",
    "title": "Female of the Species",
    "startTime": "2025-12-13T07:47:54Z",
    "source": "PLAYIT"
  },
  {
    "artist": "Jess Glynne",
    "title": "Hold My Hand",
    "startTime": "2025-12-13T07:51:10Z",
    "source": "PLAYIT"
  },
  {
    "artist": "Gnarls Barkley",
    "title": "Crazy",
    "startTime": "2025-12-13T07:54:48Z",
    "source": "PLAYIT"
  },
  {
    "artist": "Lady Gaga",
    "title": "The Dead Dance",
    "startTime": "2025-12-13T08:01:35Z",
    "source": "PLAYIT"
  },
  {
    "artist": "Taylor Swift",
    "title": "Cruel Summer",
    "startTime": "2025-12-13T08:05:46Z",
    "source": "PLAYIT"
  },
  {
    "artist": "Benson Boone",
    "title": "Sorry I'm Here For Someone Else",
    "startTime": "2025-12-13T08:08:43Z",
    "source": "PLAYIT"
  },
  {
    "artist": "Tate McRae",
    "title": "She's All I Wanna Be",
    "startTime": "2025-12-13T08:11:55Z",
    "source": "PLAYIT"
  },
  {
    "artist": "Greg Lake",
    "title": "I Believe in Father Christmas",
    "startTime": "2025-12-13T08:15:25Z",
    "source": "PLAYIT"
  },
  {
    "artist": "Sam Fender & Olivia Dean",
    "title": "Rein Me In",
    "startTime": "2025-12-13T08:23:05Z",
    "source": "PLAYIT"
  }
]