[
  {
    "artist": "Hozier",
    "title": "Too Sweet",
    "startTime": "2025-11-15T11:47:25Z",
    "source": "PLAYIT"
  },
  {
    "artist": "Katy Perry",
    "title": "Roar",
    "startTime": "2025-11-15T11:51:29Z",
    "source": "PLAYIT"
  },
  {
    "artist": "Rick Astley",
    "title": "Together Forever",
    "startTime": "2025-11-15T11:55:03Z",
    "source": "PLAYIT"
  },
  {
    "artist": "Sabrina Carpenter",
    "title": "Tears",
    "startTime": "2025-11-15T12:01:53Z",
    "source": "PLAYIT"
  },
  {
    "artist": "Chappell Roan",
    "title": "Pink Pony Club",
    "startTime": "2025-11-15T12:05:09Z",
    "source": "PLAYIT"
  },
  {
    "artist": "Pink",
    "title": "Never Gonna Not Dance Again",
    "startTime": "2025-11-15T12:09:21Z",
    "source": "PLAYIT"
  },
  {
    "artist": "Katrina & The Waves",
    "title": "Walking on Sunshine",
    "startTime": "2025-11-15T12:13:00Z",
    "source": "PLAYIT"
  },
  {
    "artist": "Marshmello & Jonas Brothers",
    "title": "Leave Before You Love Me",
    "startTime": "2025-11-15T12:21:01Z",
    "source": "PLAYIT"
  },
  {
    "artist": "Sam Fender & Olivia Dean",
    "title": "Rein Me In",
    "startTime": "2025-11-15T12:23:41Z",
    "source": "PLAYIT"
  },
  {
    "artist": "Baccara",
    "title": "Yes Sir, I Can Boogie",
    "startTime": "2025-11-15T12:27:39Z",
    "source": "PLAYIT"
  },
  {
    "artist": "Calvin Harris",
    "title": "Feel So Close",
    "startTime": "2025-11-15T12:32:09Z",
    "source": "PLAYIT"
  },
  {
    "artist": "Lewis Capaldi",
    "title": "Something In The Heavens",
    "startTime": "2025-11-15T12:35:31Z",
    "source": "PLAYIT"
  },
  {
    "artist": "David Guetta, OneRepublic",
    "title": "I Don't Wanna Wait",
    "startTime": "2025-11-15T12:43:00Z",
    "source": "PLAYIT"
  },
  {
    "artist": "Ne-Yo",
    "title": "Let Me Love You",
    "startTime": "2025-11-15T12:45:38Z",
    "source": "PLAYIT"
  },
  {
    "artist": "Lizzo",
    "title": "About Damn Time",
    "startTime": "2025-11-15T12:50:48Z",
    "source": "PLAYIT"
  },
  {
    "artist": "McFly",
    "title": "Obviously",
    "startTime": "2025-11-15T12:54:03Z",
    "source": "PLAYIT"
  },
  {
    "artist": "The Rembrandts",
    "title": "I'll Be There for You",
    "startTime": "2025-11-15T12:57:10Z",
    "source": "PLAYIT"
  },
  {
    "artist": "The Rembrandts",
    "title": "I'll Be There for You",
    "startTime": "2025-11-15T13:00:00Z",
    "source": "ALT"
  },
  {
    "artist": "1PM SMM",
    "title": "JUKEBOX LIVE - GUESS THE LINK",
    "startTime": "2025-11-15T13:00:29Z",
    "source": "ALT"
  },
  {
    "artist": "1.20PM SMM",
    "title": "MTWCS - LINDA & JAMES & CELINE DION",
    "startTime": "2025-11-15T13:20:32Z",
    "source": "ALT"
  }
]