[
  {
    "artist": "Texas",
    "title": "Getaway",
    "startTime": "2025-11-13T19:49:02Z",
    "source": "PLAYIT"
  },
  {
    "artist": "Manic Street Preachers",
    "title": "A Design for Life",
    "startTime": "2025-11-13T19:52:33Z",
    "source": "PLAYIT"
  },
  {
    "artist": "Myles Smith",
    "title": "Nice To Meet You",
    "startTime": "2025-11-13T19:56:40Z",
    "source": "PLAYIT"
  },
  {
    "artist": "Nelly Furtado",
    "title": "Promiscuous",
    "startTime": "2025-11-13T20:01:59Z",
    "source": "PLAYIT"
  },
  {
    "artist": "Sugar Ray",
    "title": "Every Morning",
    "startTime": "2025-11-13T20:05:44Z",
    "source": "PLAYIT"
  },
  {
    "artist": "The Strokes",
    "title": "Last Nite",
    "startTime": "2025-11-13T20:09:12Z",
    "source": "PLAYIT"
  },
  {
    "artist": "Fatboy Slim",
    "title": "Praise You",
    "startTime": "2025-11-13T20:12:18Z",
    "source": "PLAYIT"
  },
  {
    "artist": "Bloc Party",
    "title": "Banquet",
    "startTime": "2025-11-13T20:19:37Z",
    "source": "PLAYIT"
  },
  {
    "artist": "Lightning Seeds",
    "title": "What If...?",
    "startTime": "2025-11-13T20:22:47Z",
    "source": "PLAYIT"
  },
  {
    "artist": "Blue",
    "title": "U Make Me Wanna",
    "startTime": "2025-11-13T20:25:58Z",
    "source": "PLAYIT"
  },
  {
    "artist": "The Prodigy",
    "title": "Firestarter",
    "startTime": "2025-11-13T20:29:37Z",
    "source": "PLAYIT"
  },
  {
    "artist": "Kaiser Chiefs",
    "title": "Everything is Average Nowadays",
    "startTime": "2025-11-13T20:33:22Z",
    "source": "PLAYIT"
  },
  {
    "artist": "Len",
    "title": "Steal My Sunshine",
    "startTime": "2025-11-13T20:40:28Z",
    "source": "PLAYIT"
  },
  {
    "artist": "Christina Aguilera",
    "title": "Ain't No Other Man",
    "startTime": "2025-11-13T20:43:53Z",
    "source": "PLAYIT"
  },
  {
    "artist": "Seal",
    "title": "Crazy",
    "startTime": "2025-11-13T20:47:29Z",
    "source": "PLAYIT"
  },
  {
    "artist": "Brian McFadden",
    "title": "Irish Son",
    "startTime": "2025-11-13T20:51:44Z",
    "source": "PLAYIT"
  },
  {
    "artist": "Phats & Small",
    "title": "Turn Around",
    "startTime": "2025-11-13T20:55:48Z",
    "source": "PLAYIT"
  },
  {
    "artist": "Stardust",
    "title": "Music Sounds Better With You",
    "startTime": "2025-11-13T21:01:41Z",
    "source": "PLAYIT"
  },
  {
    "artist": "Justin Timberlake",
    "title": "Rock Your Body",
    "startTime": "2025-11-13T21:05:58Z",
    "source": "PLAYIT"
  },
  {
    "artist": "Jon Secada",
    "title": "Just Another Day",
    "startTime": "2025-11-13T21:10:17Z",
    "source": "PLAYIT"
  }
]