[
  {
    "artist": "Ed Sheeran",
    "title": "Camera",
    "startTime": "2025-11-30T07:01:51Z",
    "source": "PLAYIT"
  },
  {
    "artist": "Dermot Kennedy",
    "title": "Kiss Me",
    "startTime": "2025-11-30T07:05:55Z",
    "source": "PLAYIT"
  },
  {
    "artist": "Alex Warren",
    "title": "Eternity",
    "startTime": "2025-11-30T07:09:35Z",
    "source": "PLAYIT"
  },
  {
    "artist": "Billie Eilish",
    "title": "Birds of a Feather",
    "startTime": "2025-11-30T07:13:08Z",
    "source": "PLAYIT"
  },
  {
    "artist": "Picture This",
    "title": "It's Christmas Time",
    "startTime": "2025-11-30T07:16:38Z",
    "source": "PLAYIT"
  },
  {
    "artist": "Taylor Swift",
    "title": "Opalite",
    "startTime": "2025-11-30T07:24:07Z",
    "source": "PLAYIT"
  },
  {
    "artist": "Coldplay",
    "title": "Feels Like I'm Falling in Love",
    "startTime": "2025-11-30T07:28:02Z",
    "source": "PLAYIT"
  },
  {
    "artist": "The Kid LAROI ft Justin Bieber",
    "title": "STAY",
    "startTime": "2025-11-30T07:31:41Z",
    "source": "PLAYIT"
  },
  {
    "artist": "Gwen Stefani",
    "title": "What You Waiting For?",
    "startTime": "2025-11-30T07:34:02Z",
    "source": "PLAYIT"
  },
  {
    "artist": "Marshmello & Jonas Brothers",
    "title": "Leave Before You Love Me",
    "startTime": "2025-11-30T07:37:15Z",
    "source": "PLAYIT"
  },
  {
    "artist": "Calvin Harris & Jessie Reyez",
    "title": "Ocean",
    "startTime": "2025-11-30T07:43:55Z",
    "source": "PLAYIT"
  },
  {
    "artist": "Ocean Colour Scene",
    "title": "The Riverboat Song",
    "startTime": "2025-11-30T07:47:25Z",
    "source": "PLAYIT"
  },
  {
    "artist": "Meghan Trainor",
    "title": "Made You Look",
    "startTime": "2025-11-30T07:51:19Z",
    "source": "PLAYIT"
  },
  {
    "artist": "The Bee Gees",
    "title": "Night Fever",
    "startTime": "2025-11-30T07:53:30Z",
    "source": "PLAYIT"
  },
  {
    "artist": "Ariana Grande",
    "title": "Thank U, Next",
    "startTime": "2025-11-30T08:01:46Z",
    "source": "PLAYIT"
  },
  {
    "artist": "Shakin' Stevens",
    "title": "Merry Christmas Everyone",
    "startTime": "2025-11-30T08:05:44Z",
    "source": "PLAYIT"
  },
  {
    "artist": "Gabriella Cilmi",
    "title": "Sweet About Me",
    "startTime": "2025-11-30T08:09:23Z",
    "source": "PLAYIT"
  },
  {
    "artist": "Olivia Rodrigo",
    "title": "Good 4 U",
    "startTime": "2025-11-30T08:12:44Z",
    "source": "PLAYIT"
  },
  {
    "artist": "Myles Smith",
    "title": "Nice To Meet You",
    "startTime": "2025-11-30T08:19:52Z",
    "source": "PLAYIT"
  },
  {
    "artist": "Def Leppard",
    "title": "Animal",
    "startTime": "2025-11-30T08:22:50Z",
    "source": "PLAYIT"
  }
]