[
  {
    "artist": "Maroon 5 ft Christina Aguilera",
    "title": "Moves Like Jagger",
    "startTime": "2025-12-06T03:12:40Z",
    "source": "PLAYIT"
  },
  {
    "artist": "Dua Lipa",
    "title": "Levitating",
    "startTime": "2025-12-06T03:15:53Z",
    "source": "PLAYIT"
  },
  {
    "artist": "Frank Sinatra",
    "title": "Have Yourself a Merry Little Christmas",
    "startTime": "2025-12-06T03:23:21Z",
    "source": "PLAYIT"
  },
  {
    "artist": "The Script Featuring Will.I.Am",
    "title": "Hall of Fame",
    "startTime": "2025-12-06T03:27:13Z",
    "source": "PLAYIT"
  },
  {
    "artist": "Caity Baser",
    "title": "Running From Myself",
    "startTime": "2025-12-06T03:30:31Z",
    "source": "PLAYIT"
  },
  {
    "artist": "Kelly Clarkson",
    "title": "Underneath the Tree",
    "startTime": "2025-12-06T03:33:03Z",
    "source": "PLAYIT"
  },
  {
    "artist": "Lewis Capaldi",
    "title": "Something In The Heavens",
    "startTime": "2025-12-06T03:36:37Z",
    "source": "PLAYIT"
  },
  {
    "artist": "The Weeknd",
    "title": "Blinding Lights",
    "startTime": "2025-12-06T03:44:34Z",
    "source": "PLAYIT"
  },
  {
    "artist": "The Cure",
    "title": "In Between Days",
    "startTime": "2025-12-06T03:47:52Z",
    "source": "PLAYIT"
  },
  {
    "artist": "Teddy Swims",
    "title": "Lose Control",
    "startTime": "2025-12-06T03:50:38Z",
    "source": "PLAYIT"
  },
  {
    "artist": "Scissor Sisters",
    "title": "Comfortably Numb",
    "startTime": "2025-12-06T03:54:01Z",
    "source": "PLAYIT"
  },
  {
    "artist": "Alex Warren",
    "title": "Eternity",
    "startTime": "2025-12-06T04:01:57Z",
    "source": "PLAYIT"
  },
  {
    "artist": "Olivia Dean",
    "title": "The Christmas Song",
    "startTime": "2025-12-06T04:05:32Z",
    "source": "PLAYIT"
  },
  {
    "artist": "Becky Hill & David Guetta",
    "title": "Remember",
    "startTime": "2025-12-06T04:08:27Z",
    "source": "PLAYIT"
  },
  {
    "artist": "Gorillaz",
    "title": "Clint Eastwood (Ed Case/Sweetie Irie Refix)",
    "startTime": "2025-12-06T04:11:09Z",
    "source": "PLAYIT"
  },
  {
    "artist": "Lady Gaga & Bruno Mars",
    "title": "Die With A Smile",
    "startTime": "2025-12-06T04:14:53Z",
    "source": "PLAYIT"
  },
  {
    "artist": "Picture This",
    "title": "It's Christmas Time",
    "startTime": "2025-12-06T04:22:40Z",
    "source": "PLAYIT"
  },
  {
    "artist": "Run-DMC ft Aerosmith",
    "title": "Walk This Way",
    "startTime": "2025-12-06T04:25:57Z",
    "source": "PLAYIT"
  },
  {
    "artist": "Taylor Swift",
    "title": "Opalite",
    "startTime": "2025-12-06T04:29:23Z",
    "source": "PLAYIT"
  },
  {
    "artist": "Daft Punk",
    "title": "One More Time",
    "startTime": "2025-12-06T04:33:22Z",
    "source": "PLAYIT"
  }
]