[
  {
    "artist": "Lily Allen",
    "title": "West End Girl",
    "startTime": "2025-11-23T16:27:49Z",
    "source": "ALT",
    "live": true
  },
  {
    "artist": "Katy Perry",
    "title": "bandaids",
    "startTime": "2025-11-23T16:30:01Z",
    "source": "ALT",
    "live": true
  },
  {
    "artist": "Sabrina Carpenter",
    "title": "House Tour",
    "startTime": "2025-11-23T16:33:18Z",
    "source": "ALT",
    "live": true
  },
  {
    "artist": "Calum Scott & Whitney Houston",
    "title": "I Wanna Dance With Somebody (Who Loves Me)",
    "startTime": "2025-11-23T16:36:13Z",
    "source": "ALT",
    "live": true
  },
  {
    "artist": "Myles Smith",
    "title": "Stay (If You Wanna Dance)",
    "startTime": "2025-11-23T16:40:02Z",
    "source": "ALT",
    "live": true
  },
  {
    "artist": "Ed Sheeran",
    "title": "Camera",
    "startTime": "2025-11-23T16:45:28Z",
    "source": "ALT",
    "live": true
  },
  {
    "artist": "Taylor Swift",
    "title": "The Fate of Ophelia",
    "startTime": "2025-11-23T16:49:27Z",
    "source": "ALT",
    "live": true
  },
  {
    "artist": "Raye",
    "title": "WHERE IS MY HUSBAND?",
    "startTime": "2025-11-23T16:56:14Z",
    "source": "ALT",
    "live": true
  },
  {
    "artist": "Raye",
    "title": "WHERE IS MY HUSBAND?",
    "startTime": "2025-11-23T17:00:02Z",
    "source": "ALT",
    "live": true
  },
  {
    "artist": "Raye",
    "title": "WHERE IS MY HUSBAND?",
    "startTime": "2025-11-23T17:00:17Z",
    "source": "ALT",
    "live": true
  },
  {
    "artist": "Raye",
    "title": "WHERE IS MY HUSBAND?",
    "startTime": "2025-11-23T17:00:31Z",
    "source": "ALT",
    "live": true
  },
  {
    "artist": "Raye",
    "title": "WHERE IS MY HUSBAND?",
    "startTime": "2025-11-23T17:00:45Z",
    "source": "ALT",
    "live": true
  },
  {
    "artist": "Raye",
    "title": "WHERE IS MY HUSBAND?",
    "startTime": "2025-11-23T17:00:58Z",
    "source": "ALT",
    "live": true
  },
  {
    "artist": "Raye",
    "title": "WHERE IS MY HUSBAND?",
    "startTime": "2025-11-23T17:01:12Z",
    "source": "ALT",
    "live": true
  },
  {
    "artist": "Raye",
    "title": "WHERE IS MY HUSBAND?",
    "startTime": "2025-11-23T17:01:26Z",
    "source": "ALT",
    "live": true
  },
  {
    "artist": "Raye",
    "title": "WHERE IS MY HUSBAND?",
    "startTime": "2025-11-23T17:01:41Z",
    "source": "ALT",
    "live": true
  },
  {
    "artist": "Raye",
    "title": "WHERE IS MY HUSBAND?",
    "startTime": "2025-11-23T17:01:56Z",
    "source": "ALT",
    "live": true
  },
  {
    "artist": "Raye",
    "title": "WHERE IS MY HUSBAND?",
    "startTime": "2025-11-23T17:02:10Z",
    "source": "ALT",
    "live": true
  },
  {
    "artist": "Raye",
    "title": "WHERE IS MY HUSBAND?",
    "startTime": "2025-11-23T17:02:24Z",
    "source": "ALT",
    "live": true
  },
  {
    "artist": "Raye",
    "title": "WHERE IS MY HUSBAND?",
    "startTime": "2025-11-23T17:02:38Z",
    "source": "ALT",
    "live": true
  }
]